wiederverwendbar-0.12.0.dist-info/METADATA
wiederverwendbar-0.12.0.dist-info/WHEEL
wiederverwendbar-0.12.0.dist-info/entry_points.txt
wiederverwendbar-0.12.0.dist-info/licenses/LICENSE
wiederverwendbar/__init__.py
wiederverwendbar/_unstable/__init__.py
wiederverwendbar/_unstable/fastapi_auth/__init__.py
wiederverwendbar/_unstable/fastapi_auth/app.py
wiederverwendbar/_unstable/fastapi_auth/auth/__init__.py
wiederverwendbar/_unstable/fastapi_auth/auth/schemes/__init__.py
wiederverwendbar/_unstable/fastapi_auth/auth/schemes/base.py
wiederverwendbar/_unstable/fastapi_auth/auth/schemes/http_basic_auth.py
wiederverwendbar/_unstable/fastapi_auth/auth/schemes/oauth2_password_bearer.py
wiederverwendbar/_unstable/fastapi_auth/auth/settings.py
wiederverwendbar/_unstable/fastapi_auth/dependencies.py
wiederverwendbar/_unstable/fastapi_auth/examples/__init__.py
wiederverwendbar/_unstable/fastapi_auth/examples/fastapi/__init__.py
wiederverwendbar/_unstable/fastapi_auth/examples/fastapi/app.py
wiederverwendbar/_unstable/fastapi_auth/examples/fastapi/router.py
wiederverwendbar/_unstable/starlette_admin/__init__.py
wiederverwendbar/_unstable/starlette_admin/action_log/__init__.py
wiederverwendbar/_unstable/starlette_admin/action_log/admin.py
wiederverwendbar/_unstable/starlette_admin/action_log/logger.py
wiederverwendbar/_unstable/starlette_admin/action_log/settings.py
wiederverwendbar/_unstable/starlette_admin/action_log/statics/js/actions.js
wiederverwendbar/_unstable/starlette_admin/action_log/templates/modals/loading.html
wiederverwendbar/_unstable/starlette_admin/action_log/thread.py
wiederverwendbar/_unstable/starlette_admin/admin.py
wiederverwendbar/_unstable/starlette_admin/drop_down_icon_view/__init__.py
wiederverwendbar/_unstable/starlette_admin/drop_down_icon_view/admin.py
wiederverwendbar/_unstable/starlette_admin/drop_down_icon_view/templates/macros/views.html
wiederverwendbar/_unstable/starlette_admin/drop_down_icon_view/views.py
wiederverwendbar/_unstable/starlette_admin/form_max_fields/__init__.py
wiederverwendbar/_unstable/starlette_admin/form_max_fields/admin.py
wiederverwendbar/_unstable/starlette_admin/form_max_fields/settings.py
wiederverwendbar-0.12.0.dist-info/RECORD
