Metadata-Version: 2.1
Name: wiederverwendbar
Version: 0.12.0
Summary: A collection of scripts, classes and tools they are \"wiederverwendbar\".
Author-Email: Julius Koenig <info@bastelquartier.de>
License:                     GNU GENERAL PUBLIC LICENSE
Requires-Python: >=3.10
Requires-Dist: pydantic>=2.12.5
Requires-Dist: pydantic-settings>=2.12.0
Requires-Dist: devtools>=0.12.2
Provides-Extra: full
Requires-Dist: rich>=14.2.0; extra == "full"
Requires-Dist: typer>=0.21.1; extra == "full"
Requires-Dist: pythonping>=1.1.4; extra == "full"
Requires-Dist: mongoengine>=0.29.1; extra == "full"
Requires-Dist: nicegui>=3.5.0; extra == "full"
Requires-Dist: uvicorn>=0.40.0; extra == "full"
Requires-Dist: fastapi>=0.128.0; extra == "full"
Requires-Dist: starlette-admin[i18n]>=0.16.0; extra == "full"
Requires-Dist: pillow>=12.1.0; extra == "full"
Requires-Dist: blinker>=1.9.0; extra == "full"
Requires-Dist: kombu>=5.6.2; extra == "full"
Requires-Dist: nest-asyncio>=1.6.0; extra == "full"
Requires-Dist: sqlalchemy>=2.0.45; extra == "full"
Requires-Dist: art>=6.5; extra == "full"
Requires-Dist: email-validator>=2.3.0; extra == "full"
Requires-Dist: xmltodict>=1.0.2; extra == "full"
Requires-Dist: dicttoxml>=1.7.16; extra == "full"
Requires-Dist: requests>=2.32.5; extra == "full"
Requires-Dist: pyyaml>=6.0.3; extra == "full"
Provides-Extra: rich
Requires-Dist: rich>=14.2.0; extra == "rich"
Provides-Extra: typer
Requires-Dist: typer>=0.21.1; extra == "typer"
Requires-Dist: art>=6.5; extra == "typer"
Requires-Dist: rich>=14.2.0; extra == "typer"
Provides-Extra: mongoengine
Requires-Dist: mongoengine>=0.29.1; extra == "mongoengine"
Requires-Dist: blinker>=1.9.0; extra == "mongoengine"
Provides-Extra: uvicorn
Requires-Dist: uvicorn>=0.40.0; extra == "uvicorn"
Provides-Extra: fastapi
Requires-Dist: fastapi>=0.128.0; extra == "fastapi"
Requires-Dist: email-validator>=2.3.0; extra == "fastapi"
Provides-Extra: nicegui
Requires-Dist: nicegui>=3.5.0; extra == "nicegui"
Provides-Extra: starlette-admin
Requires-Dist: starlette-admin[i18n]>=0.16.0; extra == "starlette-admin"
Requires-Dist: pillow>=12.1.0; extra == "starlette-admin"
Requires-Dist: kombu>=5.6.2; extra == "starlette-admin"
Requires-Dist: nest-asyncio>=1.6.0; extra == "starlette-admin"
Provides-Extra: sqlalchemy
Requires-Dist: sqlalchemy>=2.0.45; extra == "sqlalchemy"
Provides-Extra: xml
Requires-Dist: xmltodict>=1.0.2; extra == "xml"
Requires-Dist: dicttoxml>=1.7.16; extra == "xml"
Provides-Extra: functions
Requires-Dist: pythonping>=1.1.4; extra == "functions"
Requires-Dist: requests>=2.32.5; extra == "functions"
Provides-Extra: yaml
Requires-Dist: pyyaml>=6.0.3; extra == "yaml"
